[
  {
    "date": "2024-01-01 00:00:00",
    "opened": [
      {
        "ticker": "JUBLINGREA.NS",
        "shares": 398.5492806185485,
        "price": 501.82,
        "amount": 200000.0
      },
      {
        "ticker": "GOODLUCK.NS",
        "shares": 213.89459274469542,
        "price": 935.04,
        "amount": 200000.0
      }
    ],
    "closed": []
  },
  {
    "date": "2024-01-08 00:00:00",
    "opened": [
      {
        "ticker": "NRAIL.NS",
        "shares": 457.93836149654254,
        "price": 436.74,
        "amount": 200000.0
      },
      {
        "ticker": "OSWALAGRO.NS",
        "shares": 5154.639175257732,
        "price": 38.8,
        "amount": 199999.99999999997
      }
    ],
    "closed": [
      {
        "ticker": "GOODLUCK.NS",
        "shares": 213.89459274469542,
        "entry_price": 935.04,
        "exit_price": 984.9899291992188,
        "return_pct": 5.342009881846637,
        "days_held": 7
      }
    ]
  },
  {
    "date": "2024-01-15 00:00:00",
    "opened": [
      {
        "ticker": "SCI.NS",
        "shares": 1161.5750958299454,
        "price": 172.18,
        "amount": 200000.0
      },
      {
        "ticker": "GUJAPOLLO.NS",
        "shares": 673.7863423508406,
        "price": 296.83,
        "amount": 200000.00000000003
      },
      {
        "ticker": "DBREALTY.NS",
        "shares": 898.2708286548394,
        "price": 222.65,
        "amount": 200000.0
      }
    ],
    "closed": [
      {
        "ticker": "OSWALAGRO.NS",
        "shares": 5154.639175257732,
        "entry_price": 38.8,
        "exit_price": 36.95000076293945,
        "return_pct": -4.768039270774598,
        "days_held": 7
      }
    ]
  },
  {
    "date": "2024-01-22 00:00:00",
    "opened": [],
    "closed": [
      {
        "ticker": "JUBLINGREA.NS",
        "shares": 398.5492806185485,
        "entry_price": 501.82,
        "exit_price": 472.8630676269531,
        "return_pct": -5.770382283098894,
        "days_held": 21
      }
    ]
  },
  {
    "date": "2024-01-29 00:00:00",
    "opened": [
      {
        "ticker": "OSWALAGRO.NS",
        "shares": 4414.602483258353,
        "price": 42.95,
        "amount": 189607.17665594624
      }
    ],
    "closed": []
  },
  {
    "date": "2024-02-05 00:00:00",
    "opened": [],
    "closed": []
  },
  {
    "date": "2024-02-12 00:00:00",
    "opened": [
      {
        "ticker": "INDOTHAI.NS",
        "shares": 556.9789461958338,
        "price": 359.08,
        "amount": 200000.0
      }
    ],
    "closed": [
      {
        "ticker": "NRAIL.NS",
        "shares": 457.93836149654254,
        "entry_price": 436.74,
        "exit_price": 456.2463684082031,
        "return_pct": 4.466357193800228,
        "days_held": 35
      },
      {
        "ticker": "GUJAPOLLO.NS",
        "shares": 673.7863423508406,
        "entry_price": 296.83,
        "exit_price": 279.3695068359375,
        "return_pct": -5.882320912327758,
        "days_held": 28
      }
    ]
  },
  {
    "date": "2024-02-19 00:00:00",
    "opened": [],
    "closed": []
  },
  {
    "date": "2024-02-26 00:00:00",
    "opened": [],
    "closed": []
  },
  {
    "date": "2024-03-04 00:00:00",
    "opened": [
      {
        "ticker": "KERNEX.NS",
        "shares": 299.73863265877924,
        "price": 657.8,
        "amount": 197168.07256294496
      }
    ],
    "closed": []
  },
  {
    "date": "2024-03-11 00:00:00",
    "opened": [],
    "closed": [
      {
        "ticker": "OSWALAGRO.NS",
        "shares": 4414.602483258353,
        "entry_price": 42.95,
        "exit_price": 41.95000076293945,
        "return_pct": -2.3282869314564603,
        "days_held": 42
      }
    ]
  },
  {
    "date": "2024-03-18 00:00:00",
    "opened": [],
    "closed": [
      {
        "ticker": "INDOTHAI.NS",
        "shares": 556.9789461958338,
        "entry_price": 359.08,
        "exit_price": 297.737060546875,
        "return_pct": -17.083362886578197,
        "days_held": 35
      },
      {
        "ticker": "KERNEX.NS",
        "shares": 299.73863265877924,
        "entry_price": 657.8,
        "exit_price": 574.9500122070312,
        "return_pct": -12.59501182623422,
        "days_held": 14
      }
    ]
  },
  {
    "date": "2024-03-25 00:00:00",
    "opened": [],
    "closed": []
  },
  {
    "date": "2024-04-01 00:00:00",
    "opened": [],
    "closed": []
  },
  {
    "date": "2024-04-08 00:00:00",
    "opened": [
      {
        "ticker": "SCI.NS",
        "shares": 870.8146471023643,
        "price": 229.67,
        "amount": 200000.0
      },
      {
        "ticker": "NRAIL.NS",
        "shares": 416.98809498988805,
        "price": 479.63,
        "amount": 200000.0
      },
      {
        "ticker": "JUBLINGREA.NS",
        "shares": 408.3466045979828,
        "price": 489.78,
        "amount": 200000.0
      },
      {
        "ticker": "OSWALAGRO.NS",
        "shares": 4273.504273504273,
        "price": 46.8,
        "amount": 199999.99999999997
      }
    ],
    "closed": []
  },
  {
    "date": "2024-04-15 00:00:00",
    "opened": [
      {
        "ticker": "INDOTHAI.NS",
        "shares": 585.2231163130944,
        "price": 341.75,
        "amount": 200000.0
      }
    ],
    "closed": [
      {
        "ticker": "SCI.NS",
        "shares": 870.8146471023643,
        "entry_price": 229.67,
        "exit_price": 210.35340881347656,
        "return_pct": -8.410585268656519,
        "days_held": 7
      },
      {
        "ticker": "OSWALAGRO.NS",
        "shares": 4273.504273504273,
        "entry_price": 46.8,
        "exit_price": 44.0,
        "return_pct": -5.982905982905977,
        "days_held": 7
      }
    ]
  },
  {
    "date": "2024-04-22 00:00:00",
    "opened": [
      {
        "ticker": "SUBROS.NS",
        "shares": 344.5305770887166,
        "price": 580.5,
        "amount": 199999.99999999997
      }
    ],
    "closed": []
  },
  {
    "date": "2024-04-29 00:00:00",
    "opened": [
      {
        "ticker": "OSWALAGRO.NS",
        "shares": 4343.105320304017,
        "price": 46.05,
        "amount": 200000.0
      }
    ],
    "closed": [
      {
        "ticker": "NRAIL.NS",
        "shares": 416.98809498988805,
        "entry_price": 479.63,
        "exit_price": 471.0731201171875,
        "return_pct": -1.7840585206956396,
        "days_held": 21
      },
      {
        "ticker": "SUBROS.NS",
        "shares": 344.5305770887166,
        "entry_price": 580.5,
        "exit_price": 620.0086059570312,
        "return_pct": 6.805961405173341,
        "days_held": 7
      }
    ]
  },
  {
    "date": "2024-05-06 00:00:00",
    "opened": [],
    "closed": [
      {
        "ticker": "INDOTHAI.NS",
        "shares": 585.2231163130944,
        "entry_price": 341.75,
        "exit_price": 330.4581604003906,
        "return_pct": -3.3041227796955006,
        "days_held": 21
      }
    ]
  },
  {
    "date": "2024-05-13 00:00:00",
    "opened": [],
    "closed": []
  },
  {
    "date": "2024-05-20 00:00:00",
    "opened": [
      {
        "ticker": "SCI.NS",
        "shares": 853.7522410996329,
        "price": 234.26,
        "amount": 200000.0
      }
    ],
    "closed": [
      {
        "ticker": "OSWALAGRO.NS",
        "shares": 4343.105320304017,
        "entry_price": 46.05,
        "exit_price": 44.29999923706055,
        "return_pct": -3.800218812029208,
        "days_held": 21
      }
    ]
  },
  {
    "date": "2024-05-27 00:00:00",
    "opened": [],
    "closed": [
      {
        "ticker": "JUBLINGREA.NS",
        "shares": 408.3466045979828,
        "entry_price": 489.78,
        "exit_price": 501.8344421386719,
        "return_pct": 2.4611952588247585,
        "days_held": 49
      }
    ]
  },
  {
    "date": "2024-06-03 00:00:00",
    "opened": [],
    "closed": []
  },
  {
    "date": "2024-06-10 00:00:00",
    "opened": [
      {
        "ticker": "NAZARA.NS",
        "shares": 246.79170779861798,
        "price": 810.4,
        "amount": 200000.0
      }
    ],
    "closed": []
  },
  {
    "date": "2024-06-17 00:00:00",
    "opened": [
      {
        "ticker": "KDDL.NS",
        "shares": 74.68343558740389,
        "price": 2677.97,
        "amount": 200000.0
      },
      {
        "ticker": "SUBROS.NS",
        "shares": 316.490750557815,
        "price": 631.93,
        "amount": 200000.0
      }
    ],
    "closed": []
  },
  {
    "date": "2024-06-24 00:00:00",
    "opened": [
      {
        "ticker": "NRAIL.NS",
        "shares": 267.2836132654283,
        "price": 461.62,
        "amount": 123383.46155558701
      }
    ],
    "closed": []
  }
]